nohm-1.0.0.data/purelib/nohm/__init__.py
nohm-1.0.0.dist-info/METADATA
nohm-1.0.0.dist-info/LICENSE.rst
nohm-1.0.0.dist-info/top_level.txt
nohm-1.0.0.dist-info/entry_points.txt
nohm-1.0.0.dist-info/WHEEL
nohm-1.0.0.dist-info/RECORD
