Metadata-Version: 2.1
Name: nohm
Version: 1.0.0
Requires-Python: >=3.7.2
Author: Nanohmics Inc
Summary: Namespace package for Nanohmics Inc
License-File: LICENSE.rst
